kivymd_extensions/__init__.py
kivymd_extensions-1.0.0.dist-info/LICENSE
kivymd_extensions-1.0.0.dist-info/METADATA
kivymd_extensions-1.0.0.dist-info/WHEEL
kivymd_extensions-1.0.0.dist-info/top_level.txt
kivymd_extensions-1.0.0.dist-info/RECORD
